src/__init__.py
src/cli.py
src/setup.py
src/.claude/agents/finter-alpha-generator.md
src/.claude/agents/finter-alpha-reviewer.md
src/.vscode/settings.json
src/templates/signal/CLAUDE.md
src/templates/signal/README.md
src/templates/signal/pyproject.toml
src/templates/signal/.claude/.mcp.json
src/templates/signal/.claude/agents.json
src/templates/signal/.vscode/settings.json
src/templates/signal/example/am.py
src/templates/signal/example/research.ipynb
finter_agent-0.1.1.dist-info/METADATA
finter_agent-0.1.1.dist-info/WHEEL
finter_agent-0.1.1.dist-info/entry_points.txt
finter_agent-0.1.1.dist-info/RECORD
