Metadata-Version: 2.4
Name: finter-agent
Version: 0.1.1
Summary: Quantitative research platform CLI with specialized agents for various research types
Requires-Python: >=3.13
Requires-Dist: click>=8.0.0
Requires-Dist: rich>=14.1.0
